LiyanHuiHtmlCssJavascriptPhpBootstrapJiaocheng/README.md
LiyanHuiHtmlCssJavascriptPhpBootstrapJiaocheng/__init__.py
LiyanHuiHtmlCssJavascriptPhpBootstrapJiaocheng/__main__.py
LiyanHuiHtmlCssJavascriptPhpBootstrapJiaocheng/file.epub
LiyanHuiHtmlCssJavascriptPhpBootstrapJiaocheng/index.html
LiyanHuiHtmlCssJavascriptPhpBootstrapJiaocheng/css/__init__.py
LiyanHuiHtmlCssJavascriptPhpBootstrapJiaocheng/css/annotations.css
LiyanHuiHtmlCssJavascriptPhpBootstrapJiaocheng/css/main.css
LiyanHuiHtmlCssJavascriptPhpBootstrapJiaocheng/css/normalize.css
LiyanHuiHtmlCssJavascriptPhpBootstrapJiaocheng/css/popup.css
LiyanHuiHtmlCssJavascriptPhpBootstrapJiaocheng/font/__init__.py
LiyanHuiHtmlCssJavascriptPhpBootstrapJiaocheng/font/fontello.eot
LiyanHuiHtmlCssJavascriptPhpBootstrapJiaocheng/font/fontello.svg
LiyanHuiHtmlCssJavascriptPhpBootstrapJiaocheng/font/fontello.ttf
LiyanHuiHtmlCssJavascriptPhpBootstrapJiaocheng/font/fontello.woff
LiyanHuiHtmlCssJavascriptPhpBootstrapJiaocheng/img/__init__.py
LiyanHuiHtmlCssJavascriptPhpBootstrapJiaocheng/img/annotator-glyph-sprite.png
LiyanHuiHtmlCssJavascriptPhpBootstrapJiaocheng/img/annotator-icon-sprite.png
LiyanHuiHtmlCssJavascriptPhpBootstrapJiaocheng/img/apple-touch-icon.png
LiyanHuiHtmlCssJavascriptPhpBootstrapJiaocheng/img/cancelfullscreen.png
LiyanHuiHtmlCssJavascriptPhpBootstrapJiaocheng/img/close.png
LiyanHuiHtmlCssJavascriptPhpBootstrapJiaocheng/img/fullscreen.png
LiyanHuiHtmlCssJavascriptPhpBootstrapJiaocheng/img/loader.gif
LiyanHuiHtmlCssJavascriptPhpBootstrapJiaocheng/img/menu-icon.png
LiyanHuiHtmlCssJavascriptPhpBootstrapJiaocheng/img/save.png
LiyanHuiHtmlCssJavascriptPhpBootstrapJiaocheng/img/saved.png
LiyanHuiHtmlCssJavascriptPhpBootstrapJiaocheng/img/settings-s.png
LiyanHuiHtmlCssJavascriptPhpBootstrapJiaocheng/img/settings.png
LiyanHuiHtmlCssJavascriptPhpBootstrapJiaocheng/img/star.png
LiyanHuiHtmlCssJavascriptPhpBootstrapJiaocheng/js/__init__.py
LiyanHuiHtmlCssJavascriptPhpBootstrapJiaocheng/js/epub.js
liyan_hui_html_css_javascript_php_bootstrap_jiaocheng-2024.2.29.0.dist-info/METADATA
liyan_hui_html_css_javascript_php_bootstrap_jiaocheng-2024.2.29.0.dist-info/WHEEL
liyan_hui_html_css_javascript_php_bootstrap_jiaocheng-2024.2.29.0.dist-info/entry_points.txt
liyan_hui_html_css_javascript_php_bootstrap_jiaocheng-2024.2.29.0.dist-info/top_level.txt
liyan_hui_html_css_javascript_php_bootstrap_jiaocheng-2024.2.29.0.dist-info/RECORD
